llama_index/readers/jira/__init__.py
llama_index/readers/jira/base.py
llama_index_readers_jira-0.5.1.dist-info/METADATA
llama_index_readers_jira-0.5.1.dist-info/WHEEL
llama_index_readers_jira-0.5.1.dist-info/licenses/LICENSE
llama_index_readers_jira-0.5.1.dist-info/RECORD
