Metadata-Version: 2.4
Name: llama-index-readers-jira
Version: 0.5.1
Summary: llama-index readers jira integration
Author-email: Your Name <you@example.com>
Maintainer: bearguy
License-Expression: MIT
License-File: LICENSE
Keywords: jira
Requires-Python: <4.0,>=3.9
Requires-Dist: jira<4,>=3.6.0
Requires-Dist: llama-index-core<0.15,>=0.13.0
